topsis/__init__.py
Topsis_Ruhi_101903744-1.0.0.dist-info/LICENSE
Topsis_Ruhi_101903744-1.0.0.dist-info/METADATA
Topsis_Ruhi_101903744-1.0.0.dist-info/WHEEL
Topsis_Ruhi_101903744-1.0.0.dist-info/top_level.txt
Topsis_Ruhi_101903744-1.0.0.dist-info/RECORD
