Metadata-Version: 2.1
Name: Topsis-Ruhi-101903744
Version: 1.0.0
Summary: A Python package implementing TOPSIS technique.
Home-page: https://github.com/ruhi-goyal/Topsis-Ruhi-101903744.git
Author: Ruhi Goyal
Author-email: rgoyal2_be19@thapar.edu
License: MIT
Platform: UNKNOWN
Classifier: License :: OSI Approved :: MIT License
Classifier: Programming Language :: Python :: 3.6
Classifier: Programming Language :: Python :: 3.7
Classifier: Programming Language :: Python :: 3.8
Classifier: Programming Language :: Python :: 3.9
License-File: LICENSE
